
{
    "$schema": "https://schema.management.azure.com/schemas/2019-04-01/deploymentParameters.json#",
    "contentVersion": "1.0.0.0",
    "parameters": {
        "location": {
            "value": "east us"
        },
        "environment": {
            "value": "secondary-prod"
        },
        "aspName": {
            "value": "asp-sec-linux"
        },
        "storageAccountName": {
            "value": "strgpsecghost"
        },
        "shareName": {
            "value": "ghostcontent"
        },
        "mountPath": {
            "value": "/var/lib/ghost/content"
        },
        "strgSKU": {
            "value": "Standard_RAGZRS"
        },
        "appName": {
            "value": "wapp-sec-ghost"
        },
        "appInsightName": {
            "value": "ai-wapp-sec"
        },
        "aspSKU": {
            "value": "S1"
        },
        "deployafd": {
            "value": false
        }

    }
}
